helper_zlib/__init__.py
helper_zlib-0.0.2.dist-info/DESCRIPTION.rst
helper_zlib-0.0.2.dist-info/METADATA
helper_zlib-0.0.2.dist-info/RECORD
helper_zlib-0.0.2.dist-info/WHEEL
helper_zlib-0.0.2.dist-info/metadata.json
helper_zlib-0.0.2.dist-info/top_level.txt
